indego/Indego.py
indego/__init__.py
indego-1.1.0.dist-info/LICENSE
indego-1.1.0.dist-info/METADATA
indego-1.1.0.dist-info/WHEEL
indego-1.1.0.dist-info/top_level.txt
indego-1.1.0.dist-info/RECORD
