Metadata-Version: 2.1
Name: indego
Version: 1.1.0
Summary: Python3 library for working with the Philadelphia Indego Bike Share API
Home-page: https://github.com/ericoc/indego-py-lib/
Author: Eric O'Callaghan
Author-email: eric@ericoc.com
License: MIT
Project-URL: Indego Philly Bike Share, https://www.rideindego.com/
Project-URL: Project maintainer, https://ericoc.com/
Keywords: philadelphia philly indego rideindego bicycle bike share bikeshare bike-share api
Platform: UNKNOWN
Classifier: Programming Language :: Python :: 3
Classifier: License :: OSI Approved :: MIT License
Classifier: Operating System :: OS Independent
Requires-Dist: requests
